django_select2_plus/__init__.py
django_select2_plus/apps.py
django_select2_plus/urls.py
django_select2_plus/views.py
django_select2_plus/widgets.py
django_select2_plus/static/django_select2_plus/css/select2-plus.css
django_select2_plus/static/django_select2_plus/js/select2-plus.js
django_select2_plus/templates/widgets/select2-plus.html
django_select2_plus-0.1.1.dist-info/licenses/LICENSE
django_select2_plus-0.1.1.dist-info/METADATA
django_select2_plus-0.1.1.dist-info/WHEEL
django_select2_plus-0.1.1.dist-info/top_level.txt
django_select2_plus-0.1.1.dist-info/RECORD
